pyarubacentral/__init__.py
pyarubacentral/auth.py
pyarubacentral/configuration.py
pyarubacentral/get_groups.py
pyarubacentral/get_networks.py
pyarubacentral/get_switches.py
pyarubacentral/get_template_vars.py
pyarubacentral/monitoring.py
pyarubacentral-1.1.45.dist-info/DESCRIPTION.rst
pyarubacentral-1.1.45.dist-info/METADATA
pyarubacentral-1.1.45.dist-info/RECORD
pyarubacentral-1.1.45.dist-info/WHEEL
pyarubacentral-1.1.45.dist-info/entry_points.txt
pyarubacentral-1.1.45.dist-info/metadata.json
pyarubacentral-1.1.45.dist-info/top_level.txt
