Metadata-Version: 2.0
Name: pyarubacentral
Version: 1.1.45
Summary: Aruba Central python module
Home-page: https://github.com/michaelrosejr/pyarubacentral
Author: Michael Rose Jr.
Author-email: michael@michaelrosejr.com
License: Apache2
Keywords: Aruba Central RESTFUL API
Platform: UNKNOWN
Classifier: Development Status :: 4 - Beta
Classifier: Intended Audience :: Developers
Classifier: Topic :: Software Development :: Build Tools
Classifier: Intended Audience :: Developers
Classifier: Intended Audience :: System Administrators
Classifier: License :: OSI Approved :: Apache Software License
Classifier: Programming Language :: Python
Classifier: Natural Language :: English
Classifier: Operating System :: OS Independent
Classifier: Topic :: Software Development :: Libraries :: Python Modules
Requires-Dist: json
Requires-Dist: requets
Provides-Extra: dev
Requires-Dist: check-manifest; extra == 'dev'
Provides-Extra: test
Requires-Dist: coverage; extra == 'test'
